influxdbpusher/__init__.py
influxdbpusher/influxdbpusher.py
influxdbpusher-0.1.3.dist-info/DESCRIPTION.rst
influxdbpusher-0.1.3.dist-info/METADATA
influxdbpusher-0.1.3.dist-info/RECORD
influxdbpusher-0.1.3.dist-info/WHEEL
influxdbpusher-0.1.3.dist-info/metadata.json
influxdbpusher-0.1.3.dist-info/top_level.txt
