Metadata-Version: 2.0
Name: influxdbpusher
Version: 0.1.3
Summary: Minimal and smart pusher of samples to InfluxDB for asyncio programs
Home-page: https://github.com/GambitResearch/influxdbpusher
Author: Gustavo Carneiro
Author-email: gjcarneiro@gmail.com
License: UNKNOWN
Platform: UNKNOWN
Classifier: Development Status :: 4 - Beta
Classifier: Programming Language :: Python
Classifier: Programming Language :: Python :: 3
Classifier: Programming Language :: Python :: 3.5
Classifier: Programming Language :: Python :: 3.6
Requires-Dist: aiohttp (>=2.0)
